mycat/__init__.py
mycat/__main__.py
mycat/main.py
mycat/images/cat.png
mycat-0.1.3.dist-info/METADATA
mycat-0.1.3.dist-info/WHEEL
mycat-0.1.3.dist-info/entry_points.txt
mycat-0.1.3.dist-info/top_level.txt
mycat-0.1.3.dist-info/RECORD
