Metadata-Version: 2.4
Name: mycat
Version: 0.1.3
Summary: Desktop Cat: Qt Overlay
Author: yumiaura
Classifier: Environment :: X11 Applications :: Qt
Classifier: Intended Audience :: End Users/Desktop
Classifier: Programming Language :: Python :: 3
Classifier: Operating System :: POSIX :: Linux
Classifier: Operating System :: Microsoft :: Windows
Classifier: Operating System :: MacOS
Requires-Python: >=3.8
Requires-Dist: PySide6>=6.5.0
